autowrapt_logger/__init__.py
autowrapt_logger/version.py
autowrapt_logger-1.6.dist-info/METADATA
autowrapt_logger-1.6.dist-info/WHEEL
autowrapt_logger-1.6.dist-info/entry_points.txt
autowrapt_logger-1.6.dist-info/top_level.txt
autowrapt_logger-1.6.dist-info/RECORD
