Metadata-Version: 2.1
Name: autowrapt-logger
Version: 1.6
Summary: logging by environment
Home-page: https://github.com/eunchong/autowrapt-logger
Author: eunchong
License: BSD
Platform: UNKNOWN
Requires-Dist: autowrapt (>=1.0)
